matxop/MatrixOperations.py
matxop/__init__.py
matxop-0.0.1.dist-info/METADATA
matxop-0.0.1.dist-info/WHEEL
matxop-0.0.1.dist-info/license.txt
matxop-0.0.1.dist-info/top_level.txt
matxop-0.0.1.dist-info/RECORD
