Metadata-Version: 2.1
Name: matxop
Version: 0.0.1
Summary: Does Matrix operation.
Author-email: Shubham Banerjee <tarubithi0203@gmail.com>
Project-URL: Homepage, https://github.com/pypa/sampleproject
Project-URL: Bug Tracker, https://github.com/pypa/sampleproject/issues
Classifier: Programming Language :: Python :: 3
Classifier: License :: OSI Approved :: MIT License
Classifier: Operating System :: OS Independent
Requires-Python: >=3.7
License-File: license.txt
